duplexPDF/__init__.py
duplexPDF/__main__.py
duplexPDF/pdf_handling.py
duplexPDF/server.py
duplexpdf-1.0.3.dist-info/METADATA
duplexpdf-1.0.3.dist-info/WHEEL
duplexpdf-1.0.3.dist-info/licenses/LICENSE
duplexpdf-1.0.3.dist-info/RECORD
