Metadata-Version: 2.4
Name: DuplexPDF
Version: 1.0.3
Summary:  Auto merge your scans to a duplex using a FTP relay server. Designed to work on Synology DSM Container Manager
Project-URL: Homepage, https://github.com/andreasmz/duplexPDF
Project-URL: Repository, https://github.com/andreasmz/duplexPDF
Project-URL: Issues, https://github.com/andreasmz/duplexPDF/issues
Author: Andreas Brilka
License-Expression: MIT
License-File: LICENSE
Keywords: Docker,NAS,duplex,scan,scanning
Classifier: Development Status :: 5 - Production/Stable
Classifier: Intended Audience :: End Users/Desktop
Classifier: Intended Audience :: System Administrators
Classifier: Programming Language :: Python :: 3
Classifier: Topic :: File Formats
Classifier: Topic :: Office/Business
Classifier: Topic :: Office/Business :: Office Suites
Classifier: Topic :: Printing
Requires-Python: >=3.11
Requires-Dist: pyftpdlib==2.0.1
Requires-Dist: pyopenssl>=24.3.0
Requires-Dist: pypdf==5.1.0
